simple_icloud/__init__.py
simple_icloud/base.py
simple_icloud-0.1.5.dist-info/LICENSE
simple_icloud-0.1.5.dist-info/METADATA
simple_icloud-0.1.5.dist-info/WHEEL
simple_icloud-0.1.5.dist-info/RECORD
