Metadata-Version: 2.3
Name: simple-iCloud
Version: 0.1.5
Summary: SimpleiCloud is a lightweight iCloud client for Python, currently focused exclusively on managing contacts.
License: Apache
Author: Luca Ferreri
Requires-Python: >=3.12,<4
Classifier: Programming Language :: Python :: 3
Classifier: Operating System :: OS Independent
Requires-Dist: lxml (>=5.4.0,<6.0.0)
Requires-Dist: requests (>=2.32.3,<3.0.0)
Requires-Dist: uuid (>=1.30,<2.0)
Requires-Dist: vobject (>=0.9.9,<0.10.0)
Project-URL: Repository, https://github.com/luca-ferreri/simple-icloud
